.gitignore
MANIFEST.in
README.md
setup.py
collective/__init__.py
collective.coreloadtests.egg-info/PKG-INFO
collective.coreloadtests.egg-info/SOURCES.txt
collective.coreloadtests.egg-info/dependency_links.txt
collective.coreloadtests.egg-info/entry_points.txt
collective.coreloadtests.egg-info/namespace_packages.txt
collective.coreloadtests.egg-info/not-zip-safe
collective.coreloadtests.egg-info/requires.txt
collective.coreloadtests.egg-info/top_level.txt
collective/coreloadtests/__init__.py
collective/coreloadtests/configure.zcml
collective/coreloadtests/exportimport/__init__.py
collective/coreloadtests/exportimport/contentcreation.py
collective/coreloadtests/exportimport/writeheavy.py
collective/coreloadtests/profiles/contentcreation/metadata.xml
collective/coreloadtests/profiles/contentcreation/users_list.txt
collective/coreloadtests/profiles/writeheavy/configure_security.txt
collective/coreloadtests/profiles/writeheavy/metadata.xml
collective/coreloadtests/tests/Contentcreation.conf
collective/coreloadtests/tests/Readonly.conf
collective/coreloadtests/tests/Writeheavy.conf
collective/coreloadtests/tests/__init__.py
collective/coreloadtests/tests/test_Contentcreation.py
collective/coreloadtests/tests/test_Readonly.py
collective/coreloadtests/tests/test_Writeheavy.py
docs/HISTORY.txt