Metadata-Version: 1.1
Name: collective.coreloadtests
Version: 0.2
Summary: Plone core load test plans
Home-page: http://pypi.python.org/pypi/collective.coreloadtests
Author: Ross Patterson
Author-email: me@rpatterson.net
License: GPL
Platform: UNKNOWN
Classifier: Programming Language :: Python
Classifier: Topic :: Software Development :: Libraries :: Python Modules
